BoogieFN/__init__.py
BoogieFN-1.0.7.dist-info/LICENSE
BoogieFN-1.0.7.dist-info/METADATA
BoogieFN-1.0.7.dist-info/WHEEL
BoogieFN-1.0.7.dist-info/entry_points.txt
BoogieFN-1.0.7.dist-info/top_level.txt
BoogieFN-1.0.7.dist-info/RECORD
