Metadata-Version: 2.1
Name: BoogieFN
Version: 1.0.7
Summary: BoogieFN Config
Home-page: https://github.com/boogiefn
Author: noteason
Author-email: support@boogiefn.cf
License: MIT
Platform: UNKNOWN
Classifier: License :: OSI Approved :: MIT License
Classifier: Programming Language :: Python :: 3
Classifier: Programming Language :: Python :: 3.7
Requires-Dist: requests
